Assitance_STT/__init__.py
assitance_STT-0.1.dist-info/METADATA
assitance_STT-0.1.dist-info/WHEEL
assitance_STT-0.1.dist-info/top_level.txt
assitance_STT-0.1.dist-info/RECORD
